README.md
ez_otlp/__init__.py
ez_otlp/log/__init__.py
ez_otlp/log/structlog_config.py
ez_otlp/open_telemetry/__init__.py
ez_otlp/open_telemetry/env_exporter.py
ez_otlp/open_telemetry/env_resource.py
ez_otlp-0.1.2.dist-info/METADATA
ez_otlp-0.1.2.dist-info/WHEEL
ez_otlp-0.1.2.dist-info/entry_points.txt
ez_otlp-0.1.2.dist-info/RECORD
