Metadata-Version: 2.4
Name: ez_otlp
Version: 0.1.2
Summary: ez-otlp is a simple tool that enables convenient use of modern monitoring systems with minimal configuration.
Project-URL: repository, https://github.com/a1403951401/ez_otlp
Author-email: Martin <martin19980418@gmail.com>
Requires-Python: >=3.12
Requires-Dist: opentelemetry-api>=1.28.2
Requires-Dist: opentelemetry-exporter-otlp>=1.28.2
Requires-Dist: opentelemetry-instrumentation-logging>=0.49b2
Requires-Dist: opentelemetry-sdk>=1.28.2
Requires-Dist: orjson>=3.10.12
Requires-Dist: psutil>=6.1.0
Requires-Dist: pydantic-settings>=2.6.1
Requires-Dist: rich>=13.9.4
